setup.cfg
setup.py
hconf/Config.py
hconf/Exceptions.py
hconf/__init__.py
hconf.egg-info/PKG-INFO
hconf.egg-info/SOURCES.txt
hconf.egg-info/dependency_links.txt
hconf.egg-info/requires.txt
hconf.egg-info/top_level.txt
hconf/Subparsers/__init__.py
hconf/Subparsers/_subparser.py
hconf/Subparsers/cmdline.py
hconf/Subparsers/dictionary.py
hconf/Subparsers/ini.py
hconf/Subparsers/json_.py
hconf/Subparsers/yaml_.py