Metadata-Version: 1.1
Name: hconf
Version: 0.0.2
Summary: A hierarchical configuration manager for parsing configurations from multiple sources.
Home-page: https://github.com/warrenspe/hconf
Author: Warren Spencer
Author-email: warrenspencer27@gmail.com
License: https://www.gnu.org/licenses/gpl-3.0.html
Download-URL: https://github.com/warrenspe/hconf/tarball/0.0.2
Keywords: configuration,config,hierarchical,cascade
Platform: Linux
Platform: Windows
